bric_analysis_libraries/__init__.py
bric_analysis_libraries/_version.py
bric_analysis_libraries/aging_data_prep.py
bric_analysis_libraries/andor_data_prep.py
bric_analysis_libraries/ec_lab_analysis.py
bric_analysis_libraries/ec_lab_data_prep.py
bric_analysis_libraries/function_matcher.py
bric_analysis_libraries/igor_jv_data_prep.py
bric_analysis_libraries/jv_analysis.py
bric_analysis_libraries/ocean_optics_data_prep.py
bric_analysis_libraries/pl_analysis.py
bric_analysis_libraries/plot.py
bric_analysis_libraries/qcm_analysis.py
bric_analysis_libraries/qcm_data_prep.py
bric_analysis_libraries/standard_functions.py
bric_analysis_libraries/jv/__init__.py
bric_analysis_libraries/jv/aging_analysis.py
bric_analysis_libraries/jv/aging_data_prep.py
bric_analysis_libraries/jv/biologic_data_prep.py
bric_analysis_libraries/jv/cycling_analysis.py
bric_analysis_libraries/jv/ec_lab_analysis.py
bric_analysis_libraries/jv/ec_lab_data_prep.py
bric_analysis_libraries/jv/igor_jv_data_prep.py
bric_analysis_libraries/jv/jv_analysis.py
bric_analysis_libraries/jv/jv_data_prep.py
bric_analysis_libraries/jv/mpp_analysis.py
bric_analysis_libraries/misc/__init__.py
bric_analysis_libraries/misc/ars_cryostat_data_prep.py
bric_analysis_libraries/misc/cary_absorption_data_prep.py
bric_analysis_libraries/misc/function_matcher.py
bric_analysis_libraries/misc/qcm_analysis.py
bric_analysis_libraries/misc/qsoft_data_prep.py
bric_analysis_libraries/misc/xrd_data_prep.py
bric_analysis_libraries/pl/__init__.py
bric_analysis_libraries/pl/andor_data_prep.py
bric_analysis_libraries/pl/blackbody_analysis.py
bric_analysis_libraries/pl/lifespec_data_prep.py
bric_analysis_libraries/pl/ocean_optics_data_prep.py
bric_analysis_libraries/pl/pl_analysis.py
bric_analysis_libraries/pl/pl_data_prep.py
bric_analysis_libraries/pl/plqy_analysis.py
bric_analysis_libraries/pl/timespec_trpl_data_prep.py
bric_analysis_libraries/pl/trpl_analysis.py
bric_analysis_libraries/scaps/__init__.py
bric_analysis_libraries-0.1.2.post1.dist-info/LICENSE
bric_analysis_libraries-0.1.2.post1.dist-info/METADATA
bric_analysis_libraries-0.1.2.post1.dist-info/WHEEL
bric_analysis_libraries-0.1.2.post1.dist-info/top_level.txt
bric_analysis_libraries-0.1.2.post1.dist-info/RECORD
