Metadata-Version: 2.1
Name: bric-analysis-libraries
Version: 0.1.2.post1
Summary: An assortment of analysis libraries.
Home-page: https://github.com/bicarlsen/analysis-libraries.git
Author: Brian Carlsen
Author-email: carlsen.bri@gmail.com
License: UNKNOWN
Platform: UNKNOWN
Classifier: Programming Language :: Python :: 3
Classifier: License :: OSI Approved :: MIT License
Classifier: Operating System :: OS Independent
License-File: LICENSE
Requires-Dist: numpy
Requires-Dist: pandas
Requires-Dist: matplotlib
Requires-Dist: scipy
Requires-Dist: h5py
